LICENSE.txt
MANIFEST.in
README.rst
bootstrap.py
buildout.cfg
setup.py
versions.cfg
cmsplugin_zinnia/__init__.py
cmsplugin_zinnia/admin.py
cmsplugin_zinnia/choices_helpers.py
cmsplugin_zinnia/cms_apps.py
cmsplugin_zinnia/cms_plugins.py
cmsplugin_zinnia/cms_toolbars.py
cmsplugin_zinnia/forms.py
cmsplugin_zinnia/menu.py
cmsplugin_zinnia/models.py
cmsplugin_zinnia/placeholder.py
cmsplugin_zinnia/settings.py
cmsplugin_zinnia/locale/fr/LC_MESSAGES/django.mo
cmsplugin_zinnia/locale/fr/LC_MESSAGES/django.po
cmsplugin_zinnia/migrations/0001_initial.py
cmsplugin_zinnia/migrations/0002_fix_djangocms330_incompatible_change.py
cmsplugin_zinnia/migrations/0003_add_default_template_value.py
cmsplugin_zinnia/migrations/0004_fix_empty_template.py
cmsplugin_zinnia/migrations/0005_update_template_field.py
cmsplugin_zinnia/migrations/0006_use_booleanfield_null_true.py
cmsplugin_zinnia/migrations/__init__.py
cmsplugin_zinnia/static/cmsplugin_zinnia/img/plugin.png
cmsplugin_zinnia/templates/cmsplugin_zinnia/authors_published.html
cmsplugin_zinnia/templates/cmsplugin_zinnia/categories_published.html
cmsplugin_zinnia/templates/cmsplugin_zinnia/categories_tree.html
cmsplugin_zinnia/templates/cmsplugin_zinnia/entries_archives_tree.html
cmsplugin_zinnia/templates/cmsplugin_zinnia/entries_calendar.html
cmsplugin_zinnia/templates/cmsplugin_zinnia/entries_random.html
cmsplugin_zinnia/templates/cmsplugin_zinnia/entry_detail.html
cmsplugin_zinnia/templates/cmsplugin_zinnia/entry_list.html
cmsplugin_zinnia/templates/cmsplugin_zinnia/entry_slider.html
cmsplugin_zinnia/templates/cmsplugin_zinnia/search_form.html
cmsplugin_zinnia/templates/cmsplugin_zinnia/tag_cloud.html
cmsplugin_zinnia/templates/cmsplugin_zinnia/tools.html
demo_cmsplugin_zinnia/__init__.py
demo_cmsplugin_zinnia/settings.py
demo_cmsplugin_zinnia/urls.py
demo_cmsplugin_zinnia/media/.gitignore
demo_cmsplugin_zinnia/migrations/__init__.py
demo_cmsplugin_zinnia/migrations/zinnia/0001_initial.py
emencia_cmsplugin_xinnia.egg-info/PKG-INFO
emencia_cmsplugin_xinnia.egg-info/SOURCES.txt
emencia_cmsplugin_xinnia.egg-info/dependency_links.txt
emencia_cmsplugin_xinnia.egg-info/not-zip-safe
emencia_cmsplugin_xinnia.egg-info/requires.txt
emencia_cmsplugin_xinnia.egg-info/top_level.txt