Metadata-Version: 2.1
Name: emencia-cmsplugin-xinnia
Version: 0.9.1
Summary: Django-CMS plugins for django-blog-xinnia
Home-page: https://github.com/emencia/emencia-cmsplugin-xinnia
Author: Emencia
Author-email: support@emencia.com
License: BSD License
Keywords: django,blog,weblog,zinnia,cms,plugins,apphook
Platform: UNKNOWN
Classifier: Framework :: Django
Classifier: Development Status :: 5 - Production/Stable
Classifier: Environment :: Web Environment
Classifier: Programming Language :: Python
Classifier: Programming Language :: Python :: 3
Classifier: Intended Audience :: Developers
Classifier: Operating System :: OS Independent
Classifier: License :: OSI Approved :: BSD License
Classifier: Topic :: Software Development :: Libraries :: Python Modules
